README.md
crdch_model.py
model/CONFIG.yaml
crdch_model-1.2.dist-info/LICENSE
crdch_model-1.2.dist-info/WHEEL
crdch_model-1.2.dist-info/METADATA
crdch_model-1.2.dist-info/RECORD
